pyftp_annek/cli.py
pyftp_annek-0.2.0.dist-info/entry_points.txt
pyftp_annek-0.2.0.dist-info/LICENSE
pyftp_annek-0.2.0.dist-info/WHEEL
pyftp_annek-0.2.0.dist-info/METADATA
pyftp_annek-0.2.0.dist-info/RECORD
