Metadata-Version: 2.1
Name: pyftp-annek
Version: 0.2.0
Summary: FTP Uploader
License: MIT
Author: Michael MacKenna
Author-email: mpmackenna@gmail.com
Requires-Python: >=3.6,<4.0
Classifier: License :: OSI Approved :: MIT License
Classifier: Programming Language :: Python :: 3
Classifier: Programming Language :: Python :: 3.6
Classifier: Programming Language :: Python :: 3.7
Classifier: Programming Language :: Python :: 3.8
Classifier: Programming Language :: Python :: 3.9
Requires-Dist: click (>=8.0.1,<9.0.0)
